MANIFEST.in
README.rst
nosekay.py
setup.py
NoseKay.egg-info/PKG-INFO
NoseKay.egg-info/SOURCES.txt
NoseKay.egg-info/dependency_links.txt
NoseKay.egg-info/entry_points.txt
NoseKay.egg-info/requires.txt
NoseKay.egg-info/top_level.txt