Metadata-Version: 1.0
Name: NoseKay
Version: 0.1.2
Summary: nose plugin for Kay framework testing
Home-page: UNKNOWN
Author: Yuku Takahashi
Author-email: taka84u9@gmail.com
License: BSD
Keywords: nose kay-framework
Platform: UNKNOWN
Classifier: Development Status :: 3 - Alpha
Classifier: License :: OSI Approved :: BSD License
Classifier: Programming Language :: Python
Classifier: Intended Audience :: Developers
Classifier: Topic :: Software Development :: Testing
